picea/__init__.py
picea/dag.py
picea/ontology.py
picea/sequence.py
picea/tree.py
picea-0.0.31.dist-info/LICENSE
picea-0.0.31.dist-info/METADATA
picea-0.0.31.dist-info/WHEEL
picea-0.0.31.dist-info/RECORD
