Metadata-Version: 2.1
Name: picea
Version: 0.0.31
Summary: A lightweight python library for working with trees and biological sequence collections
Home-page: https://github.com/holmrenser/picea
License: MIT
Author: Rens Holmer
Requires-Python: >=3.10,<3.13
Classifier: Development Status :: 3 - Alpha
Classifier: Intended Audience :: Developers
Classifier: Intended Audience :: Science/Research
Classifier: License :: OSI Approved :: MIT License
Classifier: Natural Language :: English
Classifier: Operating System :: MacOS
Classifier: Operating System :: Microsoft :: Windows
Classifier: Operating System :: POSIX
Classifier: Operating System :: Unix
Classifier: Programming Language :: Python :: 3
Classifier: Programming Language :: Python :: 3.10
Classifier: Programming Language :: Python :: 3.11
Classifier: Programming Language :: Python :: 3.12
Classifier: Topic :: Scientific/Engineering :: Bio-Informatics
Classifier: Topic :: Utilities
Requires-Dist: matplotlib (>=3.9.0,<4.0.0)
Requires-Dist: numpy (==1.26)
Project-URL: Repository, https://github.com/holmrenser/picea
